[
  { "w": "she", "t": "Personal"},
  { "w": "I", "t": "Personal"},
  { "w": "him", "t": "Personal"},
  { "w": "me", "t": "Personal"},
  { "w": "you", "t": "Personal"},
  { "w": "your", "t": "Possessive"},
  { "w": "hers", "t": "Possessive"},
  { "w": "theirs", "t": "Possessive"},
  { "w": "mine", "t": "Possessive"},
  { "w": "ours", "t": "Possessive"},
  { "w": "itself", "t": "Reflective"},
  { "w": "himself", "t": "Reflective"},
  { "w": "ourselves", "t": "Reflective"},
  { "w": "herself", "t": "Reflective"},
  { "w": "myself", "t": "Reflective"},
  { "w": "everyone", "t": "Indefinite"},
  { "w": "both", "t": "Indefinite"},
  { "w": "anybody", "t": "Indefinite"},
  { "w": "everything", "t": "Indefinite"},
  { "w": "anything", "t": "Indefinite"},
  { "w": "this", "t": "Demonstrative"},
  { "w": "those", "t": "Demonstrative"},
  { "w": "these", "t": "Demonstrative"},
  { "w": "that", "t": "Demonstrative"},
  { "w": "whoever", "t": "Relative"},
  { "w": "whose", "t": "Relative"},
  { "w": "whom", "t": "Relative"},
  { "w": "which", "t": "Relative"},
  { "w": "who", "t": "Relative"}
]